terrajinja/imports/jira/__init__.py
terrajinja/imports/jira/py.typed
terrajinja/imports/jira/_jsii/__init__.py
terrajinja/imports/jira/_jsii/jira@0.0.0.jsii.tgz
terrajinja/imports/jira/comment/__init__.py
terrajinja/imports/jira/component/__init__.py
terrajinja/imports/jira/data_jira_field/__init__.py
terrajinja/imports/jira/data_jira_jql/__init__.py
terrajinja/imports/jira/filter/__init__.py
terrajinja/imports/jira/group/__init__.py
terrajinja/imports/jira/group_membership/__init__.py
terrajinja/imports/jira/issue/__init__.py
terrajinja/imports/jira/issue_link/__init__.py
terrajinja/imports/jira/issue_link_type/__init__.py
terrajinja/imports/jira/issue_type/__init__.py
terrajinja/imports/jira/project/__init__.py
terrajinja/imports/jira/project_category/__init__.py
terrajinja/imports/jira/project_membership/__init__.py
terrajinja/imports/jira/provider/__init__.py
terrajinja/imports/jira/role/__init__.py
terrajinja/imports/jira/user/__init__.py
terrajinja/imports/jira/webhook/__init__.py
terrajinja_imports_jira-0.1.20.dist-info/LICENSE
terrajinja_imports_jira-0.1.20.dist-info/METADATA
terrajinja_imports_jira-0.1.20.dist-info/WHEEL
terrajinja_imports_jira-0.1.20.dist-info/top_level.txt
terrajinja_imports_jira-0.1.20.dist-info/RECORD
